{"_default": {"1": {"key": "next_blink_setup", "value": "2025-12-11T17:04:36.114147"}, "2": {"key": "next_janus", "value": "2025-12-11T17:04:37.124634"}, "3": {"key": "next_janus2", "value": "2025-12-11T17:04:41.204313"}, "4": {"key": "next_janus3", "value": "2025-12-11T17:04:43.674466"}, "5": {"key": "next_erda_fountain", "value": "2025-12-11T17:04:43.636577"}, "6": {"key": "regular_exp_cp", "value": "2025-12-11T14:26:43.676744"}, "7": {"key": "legion_drop", "value": "2025-12-09T16:24:32.257962"}, "8": {"key": "legion_meso", "value": "2025-12-09T14:53:14.465855"}, "9": {"key": "wap", "value": "2025-12-11T13:34:15.193497"}, "10": {"key": "eap", "value": "2025-11-24T14:52:59.936561"}, "11": {"key": "bonus_exp_cp", "value": "2025-12-11T14:26:43.676744"}}}